{
  "project_info": {
    "project_number": "483814936147",
    "project_id": "fixitservice-41067",
    "storage_bucket": "fixitservice-41067.firebasestorage.app"
  },
  "client": [
    {
      "client_info": {
        "mobilesdk_app_id": "1:483814936147:android:0d8cc1d703f6e668fb00a6",
        "android_client_info": {
          "package_name": "com.example.fixit_service"
        }
      },
      "oauth_client": [
        {
          "client_id": "483814936147-143u7sknqh3eoamb7kbnrclt9d0v61qn.apps.googleusercontent.com",
          "client_type": 3
        }
      ],
      "api_key": [
        {
          "current_key": "AIzaSyDaHg3LlF_9_XAU64zeT6WV4FOh6OJdo24"
        }
      ],
      "services": {
        "appinvite_service": {
          "other_platform_oauth_client": [
            {
              "client_id": "483814936147-143u7sknqh3eoamb7kbnrclt9d0v61qn.apps.googleusercontent.com",
              "client_type": 3
            },
            {
              "client_id": "483814936147-4c57c1ut3a31mtoijplmb8440ra6e3j9.apps.googleusercontent.com",
              "client_type": 2,
              "ios_info": {
                "bundle_id": "com.example.fixitService"
              }
            }
          ]
        }
      }
    }
  ],
  "configuration_version": "1"
}